fhconfig/__about__.py
fhconfig/__init__.py
fhconfig/files.py
fhconfig/settings.py
fhconfig/validation.py
fhconfig-0.1.0.dist-info/METADATA
fhconfig-0.1.0.dist-info/WHEEL
fhconfig-0.1.0.dist-info/licenses/LICENSE.txt
fhconfig-0.1.0.dist-info/RECORD
