Metadata-Version: 2.4
Name: fhconfig
Version: 0.1.0
Project-URL: Documentation, https://github.com/wsd/fhconfig#readme
Project-URL: Issues, https://github.com/wsd/fhconfig/issues
Project-URL: Source, https://github.com/wsd/fhconfig
Author-email: wsd <wsd@fhit.cn>
License-Expression: MIT
License-File: LICENSE.txt
Classifier: Development Status :: 4 - Beta
Classifier: Programming Language :: Python
Classifier: Programming Language :: Python :: 3.8
Classifier: Programming Language :: Python :: 3.9
Classifier: Programming Language :: Python :: 3.10
Classifier: Programming Language :: Python :: 3.11
Classifier: Programming Language :: Python :: 3.12
Classifier: Programming Language :: Python :: Implementation :: CPython
Classifier: Programming Language :: Python :: Implementation :: PyPy
Requires-Python: >=3.8
